<?xml version="1.0" encoding="UTF-8"?>
<LanguageData>
  
  <!-- EN: bite -->
  <Bite.label>menggigit</Bite.label>
  
  <!-- EN: blunt -->
  <Blunt.label>kesibukan</Blunt.label>
  
  <!-- EN: cut -->
  <Cut.label>pengadilan</Cut.label>
  
  <!-- EN: demolish -->
  <Demolish.label>menghancurkan</Demolish.label>
  
  <!-- EN: kick material in eyes -->
  <KickMaterialInEyes.label>membuang</KickMaterialInEyes.label>
  
  <!-- EN: poke -->
  <Poke.label>pengeboran</Poke.label>
  
  <!-- EN: scratch -->
  <Scratch.label>menggores</Scratch.label>
  
  <!-- EN: toxic scratch -->
  <ScratchToxic.label>Goresan beracun</ScratchToxic.label>
  
  <!-- EN: stab -->
  <Stab.label>menusuk</Stab.label>
  
  <!-- EN: toxic bite -->
  <ToxicBite.label>Gigitan beracun</ToxicBite.label>
  
</LanguageData>